dev/__init__.py
dev/cluster.py
russianwords/__init__.py
russianwords/clustering.py
RussianWordsClusters-0.0.10.dist-info/LICENSE
RussianWordsClusters-0.0.10.dist-info/METADATA
RussianWordsClusters-0.0.10.dist-info/WHEEL
RussianWordsClusters-0.0.10.dist-info/top_level.txt
RussianWordsClusters-0.0.10.dist-info/RECORD
