Metadata-Version: 2.1
Name: RussianWordsClusters
Version: 0.0.10
Summary: Clustering russian words by multiple criterias
Home-page: https://github.com/StorkST/RussianWordsClusters/
Author: Vincent Charrade
Author-email: vchd@pm.me
License: UNKNOWN
Platform: UNKNOWN
Classifier: Programming Language :: Python :: 3
Classifier: License :: OSI Approved :: MIT License
Classifier: Operating System :: OS Independent
